Metadata-Version: 2.1
Name: django-showmequeries
Version: 0.1.0
Summary: Middleware that Prints statics of DB queries to the runserver console.
Home-page: https://github.com/kaajavi/django-showmequeries
Author: Javier Guignard
Author-email: kaajavi@gmail.com
License: MIT
Keywords: django querycount queries database performance
Platform: UNKNOWN
Classifier: Development Status :: 4 - Beta
Classifier: Environment :: Web Environment
Classifier: Intended Audience :: Developers
Classifier: License :: OSI Approved :: MIT License
Classifier: Operating System :: OS Independent
Classifier: Programming Language :: Python
Classifier: Framework :: Django
Classifier: Topic :: Utilities
License-File: LICENSE.txt
License-File: AUTHORS.rst
